jsonfmt/__init__.py
jsonfmt/diff.py
jsonfmt/jsonfmt.py
jsonfmt/utils.py
jsonfmt/xml2py.py
jsonfmt-0.2.7.dist-info/LICENSE
jsonfmt-0.2.7.dist-info/METADATA
jsonfmt-0.2.7.dist-info/WHEEL
jsonfmt-0.2.7.dist-info/entry_points.txt
jsonfmt-0.2.7.dist-info/top_level.txt
jsonfmt-0.2.7.dist-info/RECORD
