Metadata-Version: 2.1
Name: jsonfmt
Version: 0.2.7
Summary: A powerful tool for pretty-printing, querying and conversion JSON documents.
Author-email: Seamile <lanhuermao@gmail.com>
License: MIT License
Project-URL: homepage, https://github.com/seamile/jsonfmt
Project-URL: repository, https://github.com/seamile/jsonfmt
Project-URL: documentation, https://seamile.github.io/jsonfmt/
Keywords: json,formatter,pretty-print,highlight,jmespath
Classifier: Development Status :: 4 - Beta
Classifier: Environment :: Console
Classifier: License :: OSI Approved :: MIT License
Classifier: Operating System :: OS Independent
Classifier: Programming Language :: Python :: 3
Classifier: Programming Language :: Python :: 3.7
Classifier: Programming Language :: Python :: 3.8
Classifier: Programming Language :: Python :: 3.9
Classifier: Programming Language :: Python :: 3.10
Classifier: Programming Language :: Python :: 3.11
Classifier: Programming Language :: Python :: 3.12
Classifier: Topic :: File Formats :: JSON
Classifier: Topic :: Printing
Classifier: Topic :: Utilities
Requires-Python: >=3.6
License-File: LICENSE
Requires-Dist: jmespath >=0.10.0
Requires-Dist: jsonpath-ng >=1.5.3
Requires-Dist: Pygments >=2.13.0
Requires-Dist: pyperclip >=1.8.2
Requires-Dist: pyyaml >=6.0
Requires-Dist: toml >=0.10.2
